yahoo_export/__about__.py
yahoo_export/__init__.py
yahoo_export/yahoo_api.py
yahoo_export/utils/__init__.py
yahoo_export/utils/utils.py
yahoo_export-3.0.1.dist-info/METADATA
yahoo_export-3.0.1.dist-info/WHEEL
yahoo_export-3.0.1.dist-info/licenses/LICENSE.txt
yahoo_export-3.0.1.dist-info/RECORD
