Metadata-Version: 2.1
Name: yahoo-export
Version: 3.0.1
Summary: Export Yahoo Fantasy Football data from historical records and live data.
Project-URL: Documentation, https://github.com/fantasy-sidelines/yahoo-export#readme
Project-URL: Issues, https://github.com/fantasy-sidelines/yahoo-export/issues
Project-URL: Source, https://github.com/fantasy-sidelines/yahoo-export
Author-email: Tim Cuddeback <cuddebtj@gmail.com>
License: MIT
License-File: LICENSE.txt
Keywords: api,data,export,fantasy,football,yahoo
Classifier: Development Status :: 4 - Beta
Classifier: License :: OSI Approved :: MIT License
Classifier: Programming Language :: Python
Classifier: Programming Language :: Python :: 3.10
Classifier: Programming Language :: Python :: 3.11
Requires-Python: >=3.10
Requires-Dist: authlib
Requires-Dist: loguru
Requires-Dist: pydantic
Requires-Dist: pydantic-settings
Requires-Dist: python-dotenv
Requires-Dist: pytz
Requires-Dist: pyyaml
Requires-Dist: ratelimit
Requires-Dist: requests
